Metadata-Version: 2.1
Name: json2oraparser
Version: 1.0.2
Summary: The 'json2oraparser' library parses a JSON file (nested upto n-th level) according to user given metadata and stores Json data into Oracle database
Home-page: https://github.com/ntpythondev/json2oraparser.git
Author: Abhishek Sinha, Samrat Ghosh, Siddhartha Bhattacharya, Shouvik Das, Sudipta Dey, Subhajit Bhar
Author-email: ntpythondev@gmail.com
License: MIT
Platform: any
Classifier: Programming Language :: Python :: 2.7
Classifier: License :: OSI Approved :: MIT License
Classifier: Operating System :: OS Independent
Classifier: Development Status :: 4 - Beta
Requires-Dist: cx-Oracle
Requires-Dist: pandas
Requires-Dist: PyYAML
